aiohttp_prometheus_exporter/__init__.py
aiohttp_prometheus_exporter/handler.py
aiohttp_prometheus_exporter/middleware.py
aiohttp_prometheus_exporter/trace.py
aiohttp_prometheus_exporter-0.2.4.dist-info/AUTHORS.rst
aiohttp_prometheus_exporter-0.2.4.dist-info/LICENSE
aiohttp_prometheus_exporter-0.2.4.dist-info/METADATA
aiohttp_prometheus_exporter-0.2.4.dist-info/WHEEL
aiohttp_prometheus_exporter-0.2.4.dist-info/top_level.txt
aiohttp_prometheus_exporter-0.2.4.dist-info/RECORD
