Metadata-Version: 2.1
Name: aiohttp-prometheus-exporter
Version: 0.2.4
Summary: Prometheus exporter for aiohttp server and client.
Home-page: https://github.com/adriankrupa/aiohttp_prometheus_exporter
Author: Adrian Krupa
Author-email: adrian.krupa91@gmail.com
License: MIT license
Keywords: aiohttp_prometheus_exporter
Platform: UNKNOWN
Classifier: Development Status :: 2 - Pre-Alpha
Classifier: Intended Audience :: Developers
Classifier: License :: OSI Approved :: MIT License
Classifier: Natural Language :: English
Classifier: Programming Language :: Python :: 3
Classifier: Programming Language :: Python :: 3.6
Classifier: Programming Language :: Python :: 3.7
Classifier: Programming Language :: Python :: 3.8
Requires-Python: >=3.6
Requires-Dist: aiohttp (>=3)
Requires-Dist: prometheus-client (>=0.6)
